Workbook

Sheet Dashboard
B1: MONTHLY BUDGET DASHBOARD
B2: Your Financial Overview at a Glance
C3: Total Income | D3: Total Expenses | E3: Remaining | F3: Savings Rate
C4: ='Monthly Input'!B8 | D4: =SUM('Monthly Input'!C11:C110) | E4: =C4-D4 | F4: =IF(C4>0,F4/C4,0)
B6: SPENDING BY CATEGORY
B7: Category | C7: Budget | D7: Actual | E7: Remaining | F7: % Used
B8: Rent / Mortgage | C8: =Categories!C4 | D8: =SUMIF('Monthly Input'!D11:D110,B8,'Monthly Input'!C11:C110) | E8: =C8-D8 | F8: =IF(C8>0,D8/C8,0)
B9: Utilities | C9: =Categories!C5 | D9: =SUMIF('Monthly Input'!D11:D110,B9,'Monthly Input'!C11:C110) | E9: =C9-D9 | F9: =IF(C9>0,D9/C9,0)
B10: Groceries | C10: =Categories!C6 | D10: =SUMIF('Monthly Input'!D11:D110,B10,'Monthly Input'!C11:C110) | E10: =C10-D10 | F10: =IF(C10>0,D10/C10,0)
B11: Transportation | C11: =Categories!C7 | D11: =SUMIF('Monthly Input'!D11:D110,B11,'Monthly Input'!C11:C110) | E11: =C11-D11 | F11: =IF(C11>0,D11/C11,0)
B12: Insurance | C12: =Categories!C8 | D12: =SUMIF('Monthly Input'!D11:D110,B12,'Monthly Input'!C11:C110) | E12: =C12-D12 | F12: =IF(C12>0,D12/C12,0)
B13: Phone / Internet | C13: =Categories!C9 | D13: =SUMIF('Monthly Input'!D11:D110,B13,'Monthly Input'!C11:C110) | E13: =C13-D13 | F13: =IF(C13>0,D13/C13,0)
B14: Minimum Debt Payments | C14: =Categories!C10 | D14: =SUMIF('Monthly Input'!D11:D110,B14,'Monthly Input'!C11:C110) | E14: =C14-D14 | F14: =IF(C14>0,D14/C14,0)
B15: Dining Out | C15: =Categories!C11 | D15: =SUMIF('Monthly Input'!D11:D110,B15,'Monthly Input'!C11:C110) | E15: =C15-D15 | F15: =IF(C15>0,D15/C15,0)
B16: Entertainment | C16: =Categories!C12 | D16: =SUMIF('Monthly Input'!D11:D110,B16,'Monthly Input'!C11:C110) | E16: =C16-D16 | F16: =IF(C16>0,D16/C16,0)
B17: Shopping | C17: =Categories!C13 | D17: =SUMIF('Monthly Input'!D11:D110,B17,'Monthly Input'!C11:C110) | E17: =C17-D17 | F17: =IF(C17>0,D17/C17,0)
B18: Subscriptions | C18: =Categories!C14 | D18: =SUMIF('Monthly Input'!D11:D110,B18,'Monthly Input'!C11:C110) | E18: =C18-D18 | F18: =IF(C18>0,D18/C18,0)
B19: Personal Care | C19: =Categories!C15 | D19: =SUMIF('Monthly Input'!D11:D110,B19,'Monthly Input'!C11:C110) | E19: =C19-D19 | F19: =IF(C19>0,D19/C19,0)
B20: Hobbies | C20: =Categories!C16 | D20: =SUMIF('Monthly Input'!D11:D110,B20,'Monthly Input'!C11:C110) | E20: =C20-D20 | F20: =IF(C20>0,D20/C20,0)
B21: Emergency Fund | C21: =Categories!C17 | D21: =SUMIF('Monthly Input'!D11:D110,B21,'Monthly Input'!C11:C110) | E21: =C21-D21 | F21: =IF(C21>0,D21/C21,0)
B22: Investments | C22: =Categories!C18 | D22: =SUMIF('Monthly Input'!D11:D110,B22,'Monthly Input'!C11:C110) | E22: =C22-D22 | F22: =IF(C22>0,D22/C22,0)
B23: Savings Goals | C23: =Categories!C19 | D23: =SUMIF('Monthly Input'!D11:D110,B23,'Monthly Input'!C11:C110) | E23: =C23-D23 | F23: =IF(C23>0,D23/C23,0)

Sheet Monthly Input
A1: MONTHLY EXPENSE TRACKER
A3: MONTHLY INCOME
A4: Salary / Wages | B4: 0
A5: Side Income | B5: 0
A6: Investment Income | B6: 0
A7: Other Income | B7: 0
A8: TOTAL INCOME | B8: =SUM(B4:B7)
A10: Date | B10: Description | C10: Amount | D10: Category | E10: Notes
A11: 2026-01-01 | B11: Monthly Rent | C11: 1500 | D11: Rent / Mortgage
A12: 2026-01-03 | B12: Grocery Store | C12: 85.5 | D12: Groceries | E12: Weekly groceries
A13: 2026-01-05 | B13: Electric Bill | C13: 65 | D13: Utilities
A14: 2026-01-07 | B14: Restaurant | C14: 45 | D14: Dining Out | E14: Dinner with friends
A15: 2026-01-10 | B15: Gas Station | C15: 50 | D15: Transportation

Sheet Categories
A1: BUDGET CATEGORIES
A3: Category | B3: Type | C3: Monthly Budget
A4: Rent / Mortgage | B4: Needs | C4: 1500
A5: Utilities | B5: Needs | C5: 150
A6: Groceries | B6: Needs | C6: 400
A7: Transportation | B7: Needs | C7: 200
A8: Insurance | B8: Needs | C8: 150
A9: Phone / Internet | B9: Needs | C9: 100
A10: Minimum Debt Payments | B10: Needs | C10: 200
A11: Dining Out | B11: Wants | C11: 150
A12: Entertainment | B12: Wants | C12: 100
A13: Shopping | B13: Wants | C13: 150
A14: Subscriptions | B14: Wants | C14: 50
A15: Personal Care | B15: Wants | C15: 50
... A19: Savings Goals | B19: Savings | C19: 100
A21: TOTAL BUDGET | C21: =SUM(C4:C19)

Sheet Annual View
A1: ANNUAL FINANCIAL OVERVIEW 2026
B3: Jan | C3: Feb | D3: Mar | E3: Apr | F3: May | G3: Jun | H3: Jul | I3: Aug | J3: Sep | K3: Oct | L3: Nov | M3: Dec | N3: TOTAL
A4: Total Income | B4: 0 | C4: 0 | D4: 0 | E4: 0 | F4: 0 | G4: 0 | H4: 0 | I4: 0 | J4: 0 | K4: 0 | L4: 0 | M4: 0 | N4: =SUM(B4:M4)
A5: Total Expenses | B5: 0 | C5: 0 | D5: 0 | E5: 0 | F5: 0 | G5: 0 | H5: 0 | I5: 0 | J5: 0 | K5: 0 | L5: 0 | M5: 0 | N5: =SUM(B5:M5)
A6: Net Savings | B6: =B4-B5 | C6: =C4-C5 | D6: =D4-D5 | E6: =E4-E5 | F6: =F4-F5 | G6: =G4-G5 | H6: =H4-H5 | I6: =I4-I5 | ... M6: =M4-M5 | N6: =SUM(B6:M6)
A7: Savings Rate | B7: =IF(B4>0,B6/B4,0) | C7: =IF(C4>0,C6/C4,0) | D7: =IF(D4>0,D6/D4,0) | E7: =IF(E4>0,E6/E4,0) | F7: =IF(F4>0,F6/F4,0) | G7: =IF(G4>0,G6/G4,0) | H7: =IF(H4>0,H6/H4,0) | I7: =IF(I4>0,I6/I4,0) | ... N7: =IF(N4>0,N6/N4,0)

Sheet Instructions
B1: HOW TO USE YOUR BUDGET TRACKER
B3: Getting Started
B4: 1. Go to the 'Categories' tab first
B5: 2. Customize the category names and budget amounts to match your needs
B6: 3. Go to 'Monthly Input' and enter your monthly income at the top
B7: 4. Start entering your daily expenses in the transaction log
B8: 5. Check your 'Dashboard' to see your spending overview!
B10: Tips for Best Results
B11: - Enter expenses as soon as they happen (or at end of each day)
B12: - Be specific with descriptions (e.g., 'Walmart groceries' not just 'store')
B13: - Review your Dashboard weekly to stay on track
B14: - Adjust your budgets monthly based on actual spending patterns
... B33: Thank you for your purchase! ★★★★★
