Workbook

Sheet Dashboard
A1: 50 / 30 / 20 BUDGET DASHBOARD
A3: Monthly Income: | B3: 5000
A5: NEEDS (50%) | B5: Target | C5: =B3*0.5 | D5: Actual | E5: =Needs!B3 | F5: Remaining | G5: =C5-E5
A7: WANTS (30%) | B7: Target | C7: =B3*0.3 | D7: Actual | E7: =Wants!B3 | F7: Remaining | G7: =C7-E7
A9: SAVINGS (20%) | B9: Target | C9: =B3*0.2 | D9: Actual | E9: =Savings!B3 | F9: Remaining | G9: =C9-E9
A12: Needs | B12: =E5
A13: Wants | B13: =E7
A14: Savings | B14: =E9

Sheet Needs
A1: NEEDS (50%) — Essential Expenses
A2: Total Spent: | B2: =SUM(C5:C104) | C2: Budget: | D2: =Dashboard!B3*0.5
A4: Date | B4: Description | C4: Amount | D4: Subcategory
A5: 2026-01-01 | B5: Rent | C5: 1500 | D5: Rent/Mortgage
A6: 2026-01-03 | B6: Electric Bill | C6: 85 | D6: Utilities
A7: 2026-01-03 | B7: Water Bill | C7: 45 | D7: Utilities
A8: 2026-01-05 | B8: Groceries | C8: 120 | D8: Groceries
A9: 2026-01-08 | B9: Gas | C9: 45 | D9: Transportation
A10: 2026-01-10 | B10: Phone Bill | C10: 65 | D10: Utilities
A11: 2026-01-12 | B11: Groceries | C11: 95 | D11: Groceries
A12: 2026-01-15 | B12: Health Insurance | C12: 200 | D12: Insurance
A13: 2026-01-18 | B13: Bus Pass | C13: 50 | D13: Transportation
A14: 2026-01-20 | B14: Groceries | C14: 110 | D14: Groceries

Sheet Wants
A1: WANTS (30%) — Lifestyle & Fun
A2: Total Spent: | B2: =SUM(C5:C104) | C2: Budget: | D2: =Dashboard!B3*0.3
A4: Date | B4: Description | C4: Amount | D4: Subcategory
A5: 2026-01-02 | B5: Coffee Shop | C5: 5.5 | D5: Dining Out
A6: 2026-01-04 | B6: Netflix | C6: 15.99 | D6: Subscriptions
A7: 2026-01-06 | B7: Restaurant Dinner | C7: 65 | D7: Dining Out
A8: 2026-01-09 | B8: Movie Tickets | C8: 28 | D8: Entertainment
A9: 2026-01-11 | B9: Spotify | C9: 10.99 | D9: Subscriptions
A10: 2026-01-14 | B10: New Shoes | C10: 89 | D10: Shopping
A11: 2026-01-17 | B11: Happy Hour | C11: 35 | D11: Dining Out
A12: 2026-01-22 | B12: Book | C12: 18 | D12: Shopping

Sheet Savings
A1: SAVINGS (20%) — Future You
A2: Total Saved: | B2: =SUM(C5:C104) | C2: Target: | D2: =Dashboard!B3*0.2
A4: Date | B4: Description | C4: Amount | D4: Destination
A5: 2026-01-01 | B5: Emergency Fund | C5: 400 | D5: Emergency Fund
A6: 2026-01-01 | B6: 401k Contribution | C6: 500 | D6: Retirement
A7: 2026-01-15 | B7: Index Fund | C7: 100 | D7: Investments

Sheet Monthly Summary
A1: MONTHLY SUMMARY
A3: Month | B3: Income | C3: Needs | D3: Wants | E3: Savings | F3: Needs % | G3: Wants % | H3: Savings % | I3: Status
A4: Jan | B4: 5000 | C4: 2315 | D4: 267.48 | E4: 1000 | F4: =IF(B4>0,C4/B4,0) | G4: =IF(B4>0,D4/B4,0) | H4: =IF(B4>0,E4/B4,0) | I4: =IF(B4=0,"—",IF(AND(F4<=0.55,G4<=0.35,H4>=0.15),"On Track","Over Budget"))
A5: Feb | B5: 5000 | C5: 2400 | D5: 1350 | E5: 1000 | F5: =IF(B5>0,C5/B5,0) | G5: =IF(B5>0,D5/B5,0) | H5: =IF(B5>0,E5/B5,0) | I5: =IF(B5=0,"—",IF(AND(F5<=0.55,G5<=0.35,H5>=0.15),"On Track","Over Budget"))
A6: Mar | B6: 5200 | C6: 2500 | D6: 1400 | E6: 1050 | F6: =IF(B6>0,C6/B6,0) | G6: =IF(B6>0,D6/B6,0) | H6: =IF(B6>0,E6/B6,0) | I6: =IF(B6=0,"—",IF(AND(F6<=0.55,G6<=0.35,H6>=0.15),"On Track","Over Budget"))
A7: Apr | B7: 5000 | C7: 0 | D7: 0 | E7: 0 | F7: =IF(B7>0,C7/B7,0) | G7: =IF(B7>0,D7/B7,0) | H7: =IF(B7>0,E7/B7,0) | I7: =IF(B7=0,"—",IF(AND(F7<=0.55,G7<=0.35,H7>=0.15),"On Track","Over Budget"))
A8: May | B8: 5000 | C8: 0 | D8: 0 | E8: 0 | F8: =IF(B8>0,C8/B8,0) | G8: =IF(B8>0,D8/B8,0) | H8: =IF(B8>0,E8/B8,0) | I8: =IF(B8=0,"—",IF(AND(F8<=0.55,G8<=0.35,H8>=0.15),"On Track","Over Budget"))
A9: Jun | B9: 5000 | C9: 0 | D9: 0 | E9: 0 | F9: =IF(B9>0,C9/B9,0) | G9: =IF(B9>0,D9/B9,0) | H9: =IF(B9>0,E9/B9,0) | I9: =IF(B9=0,"—",IF(AND(F9<=0.55,G9<=0.35,H9>=0.15),"On Track","Over Budget"))
A10: Jul | B10: 5000 | C10: 0 | D10: 0 | E10: 0 | F10: =IF(B10>0,C10/B10,0) | G10: =IF(B10>0,D10/B10,0) | H10: =IF(B10>0,E10/B10,0) | I10: =IF(B10=0,"—",IF(AND(F10<=0.55,G10<=0.35,H10>=0.15),"On Track","Over Budget"))
A11: Aug | B11: 5000 | C11: 0 | D11: 0 | E11: 0 | F11: =IF(B11>0,C11/B11,0) | G11: =IF(B11>0,D11/B11,0) | H11: =IF(B11>0,E11/B11,0) | I11: =IF(B11=0,"—",IF(AND(F11<=0.55,G11<=0.35,H11>=0.15),"On Track","Over Budget"))
A12: Sep | B12: 5200 | C12: 0 | D12: 0 | E12: 0 | F12: =IF(B12>0,C12/B12,0) | G12: =IF(B12>0,D12/B12,0) | H12: =IF(B12>0,E12/B12,0) | I12: =IF(B12=0,"—",IF(AND(F12<=0.55,G12<=0.35,H12>=0.15),"On Track","Over Budget"))
A13: Oct | B13: 5000 | C13: 0 | D13: 0 | E13: 0 | F13: =IF(B13>0,C13/B13,0) | G13: =IF(B13>0,D13/B13,0) | H13: =IF(B13>0,E13/B13,0) | I13: =IF(B13=0,"—",IF(AND(F13<=0.55,G13<=0.35,H13>=0.15),"On Track","Over Budget"))
A14: Nov | B14: 5500 | C14: 0 | D14: 0 | E14: 0 | F14: =IF(B14>0,C14/B14,0) | G14: =IF(B14>0,D14/B14,0) | H14: =IF(B14>0,E14/B14,0) | I14: =IF(B14=0,"—",IF(AND(F14<=0.55,G14<=0.35,H14>=0.15),"On Track","Over Budget"))
A15: Dec | B15: 6000 | C15: 0 | D15: 0 | E15: 0 | F15: =IF(B15>0,C15/B15,0) | G15: =IF(B15>0,D15/B15,0) | H15: =IF(B15>0,E15/B15,0) | I15: =IF(B15=0,"—",IF(AND(F15<=0.55,G15<=0.35,H15>=0.15),"On Track","Over Budget"))

Sheet Instructions
A1: HOW TO USE THE 50/30/20 BUDGET
B3: The 50/30/20 Rule
B4: 50% NEEDS: Essential expenses you can't avoid (rent, food, bills)
B5: 30% WANTS: Lifestyle spending (dining, entertainment, shopping)
B6: 20% SAVINGS: Building your future (emergency fund, investments, debt payoff)
B8: Getting Started
B9: 1. Enter your monthly income on the Dashboard
B10: 2. Log needs expenses in the 'Needs' tab
B11: 3. Log wants expenses in the 'Wants' tab
B12: 4. Log savings/investments in the 'Savings' tab
B13: 5. Dashboard updates automatically!
B15: Tips
B16: - Check Dashboard weekly to stay on track
... B24: The 50/30/20 rule is a guideline — adjust to fit YOUR life!
