Workbook

Sheet Dashboard
A1: FREELANCER INCOME DASHBOARD
B3: YTD Revenue | D3: YTD Expenses | F3: YTD Net Profit
B4: ='Monthly Report'!B16 | D4: ='Monthly Report'!C16 | F4: ='Monthly Report'!D16
B5: Total Clients | D5: Avg Project Value | F5: Tax Set-Aside
B6: 5 | D6: ='Monthly Report'!B16/8 | F6: ='Monthly Report'!E16
B9: Acme Corp | C9: 7500
B10: TechStart Inc | C10: 5100
B11: Green Media | C11: 3600
B12: BlueSky LLC | C12: 4500
B13: FastFood Co | C13: 3000

Sheet Clients
A1: CLIENT DIRECTORY
A3: Client Name | B3: Contact Person | C3: Email | D3: Rate Type | E3: Rate ($) | F3: Status | G3: Total Billed | H3: Notes
A4: Acme Corp | B4: John Smith | C4: john@acme.com | D4: Project | E4: 2500 | F4: Active | G4: 7500 | H4: Web redesign
A5: TechStart Inc | B5: Sarah Lee | C5: sarah@techstart.com | D5: Hourly | E5: 85 | F5: Active | G5: 5100 | H5: Ongoing dev
A6: Green Media | B6: Mike Chen | C6: mike@greenmedia.com | D6: Project | E6: 1800 | F6: Active | G6: 3600 | H6: Social media
A7: BlueSky LLC | B7: Emma Davis | C7: emma@bluesky.com | D7: Hourly | E7: 75 | F7: Active | G7: 4500 | H7: Consulting
A8: FastFood Co | B8: Tom Wilson | C8: tom@fastfood.com | D8: Project | E8: 3000 | F8: Completed | G8: 3000 | H8: Menu redesign

Sheet Projects
A1: PROJECT LOG
A3: Project | B3: Client | C3: Start Date | D3: End Date | E3: Hours | F3: Rate | G3: Total | H3: Status | I3: Invoice #
A4: Website Redesign v1 | B4: Acme Corp | C4: 2026-01-05 | D4: 2026-01-25 | E4: 0 | F4: 2500 | G4: 2500 | H4: Paid | I4: INV-001
A5: Website Redesign v2 | B5: Acme Corp | C5: 2026-02-01 | D5: 2026-02-20 | E5: 0 | F5: 2500 | G5: 2500 | H5: Paid | I5: INV-004
A6: App Development | B6: TechStart Inc | C6: 2026-01-10 | D6: 2026-02-28 | E6: 60 | F6: 85 | G6: 5100 | H6: Paid | I6: INV-002
A7: Social Campaign Q1 | B7: Green Media | C7: 2026-01-15 | D7: 2026-02-15 | E7: 0 | F7: 1800 | G7: 1800 | H7: Paid | I7: INV-003
A8: Social Campaign Q2 | B8: Green Media | C8: 2026-03-01 | D8: 2026-03-31 | E8: 0 | F8: 1800 | G8: 1800 | H8: Invoiced | I8: INV-006
A9: Strategy Consult | B9: BlueSky LLC | C9: 2026-01-20 | D9: 2026-03-20 | E9: 60 | F9: 75 | G9: 4500 | H9: Invoiced | I9: INV-005
A10: Menu Design | B10: FastFood Co | C10: 2026-02-10 | D10: 2026-03-10 | E10: 0 | F10: 3000 | G10: 3000 | H10: Paid | I10: INV-007
A11: Website Redesign v3 | B11: Acme Corp | C11: 2026-03-15 | E11: 0 | F11: 2500 | G11: 2500 | H11: Pending
A12: TOTAL | G12: =SUM(G4:G11)

Sheet Invoices
A1: INVOICE TRACKER
A3: Invoice # | B3: Client | C3: Amount | D3: Date Sent | E3: Due Date | F3: Date Paid | G3: Status
A4: INV-001 | B4: Acme Corp | C4: 2500 | D4: 2026-01-26 | E4: 2026-02-25 | F4: 2026-02-10 | G4: Paid
A5: INV-002 | B5: TechStart Inc | C5: 5100 | D5: 2026-03-01 | E5: 2026-03-31 | F5: 2026-03-15 | G5: Paid
A6: INV-003 | B6: Green Media | C6: 1800 | D6: 2026-02-16 | E6: 2026-03-16 | F6: 2026-03-01 | G6: Paid
A7: INV-004 | B7: Acme Corp | C7: 2500 | D7: 2026-02-21 | E7: 2026-03-21 | F7: 2026-03-10 | G7: Paid
A8: INV-005 | B8: BlueSky LLC | C8: 4500 | D8: 2026-03-21 | E8: 2026-04-20 | G8: Sent
A9: INV-006 | B9: Green Media | C9: 1800 | D9: 2026-04-01 | E9: 2026-05-01 | G9: Sent
A10: INV-007 | B10: FastFood Co | C10: 3000 | D10: 2026-03-11 | E10: 2026-04-10 | F10: 2026-03-28 | G10: Paid
A11: TOTAL | C11: =SUM(C4:C10)

Sheet Tax Estimator
A1: QUARTERLY TAX ESTIMATOR
A3: Estimated Tax Rate: | B3: 0.25
A5: Quarter | B5: Gross Income | C5: Estimated Tax | D5: Due Date | E5: Status
A6: Q1 (Jan-Mar) | B6: 23700 | C6: =B6*$B$3 | D6: 2026-04-15 | E6: Upcoming
A7: Q2 (Apr-Jun) | B7: 0 | C7: =B7*$B$3 | D7: 2026-06-15 | E7: Pending
A8: Q3 (Jul-Sep) | B8: 0 | C8: =B8*$B$3 | D8: 2026-09-15 | E8: Pending
A9: Q4 (Oct-Dec) | B9: 0 | C9: =B9*$B$3 | D9: 2027-01-15 | E9: Pending
A10: ANNUAL TOTAL | B10: =SUM(B6:B9) | C10: =SUM(C6:C9)

Sheet Monthly Report
A1: MONTHLY INCOME REPORT
A3: Month | B3: Revenue | C3: Business Expenses | D3: Net Profit | E3: Tax Set-Aside | F3: Take-Home
A4: January | B4: 4300 | C4: 350 | D4: =B4-C4 | E4: =D4*'Tax Estimator'!$B$3 | F4: =D4-E4
A5: February | B5: 6800 | C5: 420 | D5: =B5-C5 | E5: =D5*'Tax Estimator'!$B$3 | F5: =D5-E5
A6: March | B6: 12600 | C6: 580 | D6: =B6-C6 | E6: =D6*'Tax Estimator'!$B$3 | F6: =D6-E6
A7: April | B7: 0 | C7: 200 | D7: =B7-C7 | E7: =D7*'Tax Estimator'!$B$3 | F7: =D7-E7
A8: May | B8: 0 | C8: 200 | D8: =B8-C8 | E8: =D8*'Tax Estimator'!$B$3 | F8: =D8-E8
A9: June | B9: 0 | C9: 200 | D9: =B9-C9 | E9: =D9*'Tax Estimator'!$B$3 | F9: =D9-E9
A10: July | B10: 0 | C10: 200 | D10: =B10-C10 | E10: =D10*'Tax Estimator'!$B$3 | F10: =D10-E10
A11: August | B11: 0 | C11: 200 | D11: =B11-C11 | E11: =D11*'Tax Estimator'!$B$3 | F11: =D11-E11
A12: September | B12: 0 | C12: 200 | D12: =B12-C12 | E12: =D12*'Tax Estimator'!$B$3 | F12: =D12-E12
A13: October | B13: 0 | C13: 200 | D13: =B13-C13 | E13: =D13*'Tax Estimator'!$B$3 | F13: =D13-E13
A14: November | B14: 0 | C14: 200 | D14: =B14-C14 | E14: =D14*'Tax Estimator'!$B$3 | F14: =D14-E14
A15: December | B15: 0 | C15: 200 | D15: =B15-C15 | E15: =D15*'Tax Estimator'!$B$3 | F15: =D15-E15
A16: TOTAL | B16: =SUM(B4:B15) | C16: =SUM(C4:C15) | D16: =SUM(D4:D15) | E16: =SUM(E4:E15) | F16: =SUM(F4:F15)

Sheet Instructions
A1: HOW TO USE YOUR FREELANCER INCOME TRACKER
B3: Getting Started
B4: 1. Add your clients in the 'Clients' tab
B5: 2. Log your projects in the 'Projects' tab
B6: 3. Track invoices in the 'Invoices' tab
B7: 4. Set your tax rate in 'Tax Estimator'
B8: 5. Check Dashboard for your complete overview!
B10: Monthly Routine
B11: - Log all new projects and update statuses
B12: - Send invoices promptly and track in Invoices tab
B13: - Update Monthly Report with actual revenue
B14: - Review tax set-aside quarterly
B16: Tips
... B24: Thank you for your purchase!
